k7sfunc/__init__.py
k7sfunc/__main__.py
k7sfunc/_internal.py
k7sfunc/mod_dbdn.py
k7sfunc/mod_etc.py
k7sfunc/mod_fmt.py
k7sfunc/mod_helper.py
k7sfunc/mod_memc.py
k7sfunc/mod_mix.py
k7sfunc/mod_scale.py
k7sfunc/_external/__init__.py
k7sfunc/_external/dfttest2.py
k7sfunc/_external/mvsfunc.py
k7sfunc/_external/nnedi3_resample.py
k7sfunc/_external/qtgmc.py
k7sfunc/_external/vsmlrt.py
k7sfunc-1.2.1.dist-info/licenses/LICENSE
k7sfunc-1.2.1.dist-info/METADATA
k7sfunc-1.2.1.dist-info/WHEEL
k7sfunc-1.2.1.dist-info/top_level.txt
k7sfunc-1.2.1.dist-info/RECORD
