Metadata-Version: 2.4
Name: k7sfunc
Version: 1.2.1
Summary: VapourSynth video processing functions optimized for media players
Author: hooke007
License-Expression: GPL-3.0-or-later
Project-URL: Homepage, https://github.com/hooke007/K7sfunc
Project-URL: Documentation, https://github.com/hooke007/mpv_PlayKit/wiki/3_K7sfunc
Project-URL: Repository, https://github.com/hooke007/K7sfunc
Project-URL: Issues, https://github.com/hooke007/mpv_PlayKit/discussions
Keywords: vapoursynth,video,processing,superresolution,interpolation
Classifier: Development Status :: 5 - Production/Stable
Classifier: Intended Audience :: Developers
Classifier: Intended Audience :: End Users/Desktop
Classifier: Topic :: Multimedia :: Video
Classifier: Topic :: Scientific/Engineering :: Image Processing
Classifier: Programming Language :: Python :: 3
Requires-Python: >=3.10
License-File: LICENSE
Provides-Extra: ai
Requires-Dist: onnx; extra == "ai"
Provides-Extra: dev
Requires-Dist: build; extra == "dev"
Requires-Dist: twine; extra == "dev"
Requires-Dist: pytest; extra == "dev"
Provides-Extra: all
Requires-Dist: onnx; extra == "all"
Requires-Dist: vapoursynth>=57; extra == "all"
Dynamic: license-file
